newspaper_scraper/__init__.py
newspaper_scraper/constants.py
newspaper_scraper/database.py
newspaper_scraper/scraper.py
newspaper_scraper/settings.py
newspaper_scraper/sites/__init__.py
newspaper_scraper/sites/bild.py
newspaper_scraper/sites/handelsblatt.py
newspaper_scraper/sites/spiegel.py
newspaper_scraper/sites/sueddeutsche.py
newspaper_scraper/sites/tagesspiegel.py
newspaper_scraper/sites/welt.py
newspaper_scraper/sites/zeit.py
newspaper_scraper/utils/__init__.py
newspaper_scraper/utils/logger.py
newspaper_scraper/utils/utils.py
newspaper_scraper-0.2.1.dist-info/LICENSE
newspaper_scraper-0.2.1.dist-info/METADATA
newspaper_scraper-0.2.1.dist-info/WHEEL
newspaper_scraper-0.2.1.dist-info/top_level.txt
newspaper_scraper-0.2.1.dist-info/RECORD
