Metadata-Version: 2.1
Name: newspaper-scraper
Version: 0.2.1
Summary: The all-in-one Python package for seamless newspaper article indexing, scraping, and processing – supports public and premium content!
Author-email: Lukas Trippe <lkstrp@pm.me>
License: MIT License
Project-URL: Homepage, https://github.com/lkstrp/newspaper-scraper
Keywords: newspaper,article,scraper,index,process,nlp,wrapper
Classifier: License :: OSI Approved :: MIT License
Classifier: Programming Language :: Python
Classifier: Programming Language :: Python :: 3
Requires-Python: >=3.8
License-File: LICENSE
Requires-Dist: pandas
Requires-Dist: selenium
Requires-Dist: beautifulsoup4
Requires-Dist: goose3 (==3.1.11)
Requires-Dist: tqdm
Provides-Extra: nlp
Requires-Dist: spacy ; extra == 'nlp'
